{
  "code" : "13.94Z",
  "libelle" : "Fabrication de ficelles, cordes et filets",
  "niveau" : "sousClasse",
  "parents" : [ "C", "13", "13.9", "13.94" ],
  "comprend" : "\n    <div:div xmlns:div=\"http://www.w3.org/1999/xhtml\" xmlns=\"http://www.w3.org/1999/xhtml\" xmlns:owl=\"http://www.w3.org/2002/07/owl#\" xmlns:rdf=\"http://www.w3.org/1999/02/22-rdf-syntax-ns#\" xmlns:fn=\"http://www.w3.org/2005/xpath-functions#\" xmlns:xsd=\"http://www.w3.org/2001/XMLSchema#\" xmlns:rdfs=\"http://www.w3.org/2000/01/rdf-schema#\" xmlns:sesame=\"http://www.openrdf.org/schema/sesame#\">\n        <ul class=\"list1\">\n            <li>\n                <p>la fabrication de ficelles, cordes et cordages, même imprégnés, enduits ou recouverts ou gainés de caoutchouc ou de matière plastique</p>\n            </li>\n            <li>\n                <p>la fabrication de filets à mailles nouées obtenus à partir de ficelles, de cordes ou de cordages</p>\n            </li>\n            <li>\n                <p>la fabrication d'articles de corderie :</p>\n                <ul class=\"list1\">\n                    <li>\n                        <p>défenses de bateaux, coussins de déchargement, élingues, brides de chargement, cordes ou câbles équipés d'anneaux métalliques, etc.</p>\n                    </li>\n                </ul>\n            </li>\n            <li>\n                <p>la fabrication de filets confectionnés pour la pêche</p>\n            </li>\n        </ul>\n    </div:div>\n",
  "noteGenerale" : null,
  "neComprendPas" : "\n    <div:div xmlns:div=\"http://www.w3.org/1999/xhtml\" xmlns=\"http://www.w3.org/1999/xhtml\" xmlns:owl=\"http://www.w3.org/2002/07/owl#\" xmlns:rdf=\"http://www.w3.org/1999/02/22-rdf-syntax-ns#\" xmlns:fn=\"http://www.w3.org/2005/xpath-functions#\" xmlns:xsd=\"http://www.w3.org/2001/XMLSchema#\" xmlns:rdfs=\"http://www.w3.org/2000/01/rdf-schema#\" xmlns:sesame=\"http://www.openrdf.org/schema/sesame#\">\n        <ul class=\"list1\">\n            <li>\n                <p>la fabrication de filets à cheveux (cf. \n                    <a href=\"http://dvrmessnclas01.ad.insee.intra:8080/datalift/codes/nafr2/sousClasse/14.19Z\">14.19Z</a>)</p>\n            </li>\n            <li>\n                <p>la fabrication de câbles métalliques (cf. \n                    <a href=\"http://dvrmessnclas01.ad.insee.intra:8080/datalift/codes/nafr2/sousClasse/25.93Z\">25.93Z</a>)</p>\n            </li>\n            <li>\n                <p>la fabrication de filets montés pour la pratique des sports (cf. \n                    <a href=\"http://dvrmessnclas01.ad.insee.intra:8080/datalift/codes/nafr2/sousClasse/32.30Z\">32.30Z</a>)</p>\n            </li>\n        </ul>\n    </div:div>\n"
}
