{
  "code" : "32.20Z",
  "libelle" : "Fabrication d'instruments de musique",
  "niveau" : "sousClasse",
  "parents" : [ "C", "32", "32.2", "32.20" ],
  "comprend" : "\n    <div:div xmlns:div=\"http://www.w3.org/1999/xhtml\" xmlns=\"http://www.w3.org/1999/xhtml\" xmlns:owl=\"http://www.w3.org/2002/07/owl#\" xmlns:rdf=\"http://www.w3.org/1999/02/22-rdf-syntax-ns#\" xmlns:fn=\"http://www.w3.org/2005/xpath-functions#\" xmlns:xsd=\"http://www.w3.org/2001/XMLSchema#\" xmlns:rdfs=\"http://www.w3.org/2000/01/rdf-schema#\" xmlns:sesame=\"http://www.openrdf.org/schema/sesame#\">\n        <ul class=\"list1\">\n            <li>\n                <p>la fabrication d'instruments à cordes</p>\n            </li>\n            <li>\n                <p>la fabrication d'instruments à cordes à clavier, y compris les pianos automatiques</p>\n            </li>\n            <li>\n                <p>la fabrication d'orgues à tuyaux et à clavier, y compris les harmoniums et les instruments similaires à clavier et à anches libres métalliques</p>\n            </li>\n            <li>\n                <p>la fabrication d'accordéons et d'instruments similaires, y compris les harmonicas à bouche</p>\n            </li>\n            <li>\n                <p>la fabrication d'instruments à vent</p>\n            </li>\n            <li>\n                <p>la fabrication d'instruments de musique à percussion</p>\n            </li>\n            <li>\n                <p>la fabrication d'instruments de musique dont le son est produit électroniquement</p>\n            </li>\n            <li>\n                <p>la fabrication de boîtes à musique, d'orchestrions, d'orgues de Barbarie, etc.</p>\n            </li>\n            <li>\n                <p>la fabrication de parties et d'accessoires d'instruments de musique :</p>\n                <ul class=\"list1\">\n                    <li>\n                        <p>métronomes, diapasons, cartes, disques et rouleaux pour instruments mécaniques, etc.</p>\n                    </li>\n                </ul>\n            </li>\n        </ul>\n    </div:div>\n",
  "noteGenerale" : null,
  "comprendAussi" : "\n    <div:div xmlns:div=\"http://www.w3.org/1999/xhtml\" xmlns=\"http://www.w3.org/1999/xhtml\" xmlns:owl=\"http://www.w3.org/2002/07/owl#\" xmlns:rdf=\"http://www.w3.org/1999/02/22-rdf-syntax-ns#\" xmlns:fn=\"http://www.w3.org/2005/xpath-functions#\" xmlns:xsd=\"http://www.w3.org/2001/XMLSchema#\" xmlns:rdfs=\"http://www.w3.org/2000/01/rdf-schema#\" xmlns:sesame=\"http://www.openrdf.org/schema/sesame#\">\n        <ul class=\"list1\">\n            <li>\n                <p>la fabrication de sifflets, de cornes d'appel et d'autres instruments d'appel ou de signalisation à bouche</p>\n            </li>\n        </ul>\n    </div:div>\n",
  "neComprendPas" : "\n    <div:div xmlns:div=\"http://www.w3.org/1999/xhtml\" xmlns=\"http://www.w3.org/1999/xhtml\" xmlns:owl=\"http://www.w3.org/2002/07/owl#\" xmlns:rdf=\"http://www.w3.org/1999/02/22-rdf-syntax-ns#\" xmlns:fn=\"http://www.w3.org/2005/xpath-functions#\" xmlns:xsd=\"http://www.w3.org/2001/XMLSchema#\" xmlns:rdfs=\"http://www.w3.org/2000/01/rdf-schema#\" xmlns:sesame=\"http://www.openrdf.org/schema/sesame#\">\n        <ul class=\"list1\">\n            <li>\n                <p>la reproduction de bandes et de disques contenant des enregistrements sonores et vidéo préenregistrés (cf. \n                    <a href=\"http://dvrmessnclas01.ad.insee.intra:8080/datalift/codes/nafr2/sousClasse/18.20Z\">18.20Z</a>)</p>\n            </li>\n            <li>\n                <p>la fabrication de microphones, d'amplificateurs, de haut-parleurs, d'écouteurs et d'articles similaires (cf. \n                    <a href=\"http://dvrmessnclas01.ad.insee.intra:8080/datalift/codes/nafr2/sousClasse/26.40Z\">26.40Z</a>)</p>\n            </li>\n            <li>\n                <p>la fabrication d'électrophones, de magnétophones et d'appareils similaires (cf. \n                    <a href=\"http://dvrmessnclas01.ad.insee.intra:8080/datalift/codes/nafr2/sousClasse/26.40Z\">26.40Z</a>)</p>\n            </li>\n            <li>\n                <p>la fabrication d'instruments ayant le caractère de jouets (cf. \n                    <a href=\"http://dvrmessnclas01.ad.insee.intra:8080/datalift/codes/nafr2/sousClasse/32.40Z\">32.40Z</a>)</p>\n            </li>\n            <li>\n                <p>la restauration d'orgues et d'autres instruments de musique historiques (cf. \n                    <a href=\"http://dvrmessnclas01.ad.insee.intra:8080/datalift/codes/nafr2/sousClasse/33.19Z\">33.19Z</a>)</p>\n            </li>\n            <li>\n                <p>la publication de bandes et de disques contenant des enregistrements sonores et vidéo préenregistrés (cf. \n                    <a href=\"http://dvrmessnclas01.ad.insee.intra:8080/datalift/codes/nafr2/sousClasse/59.20Z\">59.20Z</a>)</p>\n            </li>\n            <li>\n                <p>l'accordage de piano (cf. \n                    <a href=\"http://dvrmessnclas01.ad.insee.intra:8080/datalift/codes/nafr2/sousClasse/95.29Z\">95.29Z</a>)</p>\n            </li>\n        </ul>\n    </div:div>\n"
}
