{
  "code" : "L",
  "libelle" : "Activités immobilières",
  "niveau" : "section",
  "enfants" : [ "68" ],
  "noteGenerale" : "\n    <div:div xmlns:div=\"http://www.w3.org/1999/xhtml\" xmlns=\"http://www.w3.org/1999/xhtml\" xmlns:owl=\"http://www.w3.org/2002/07/owl#\" xmlns:rdf=\"http://www.w3.org/1999/02/22-rdf-syntax-ns#\" xmlns:fn=\"http://www.w3.org/2005/xpath-functions#\" xmlns:xsd=\"http://www.w3.org/2001/XMLSchema#\" xmlns:rdfs=\"http://www.w3.org/2000/01/rdf-schema#\" xmlns:sesame=\"http://www.openrdf.org/schema/sesame#\">\n        <p>Cette section comprend les activités de bailleurs, d'agents et/ou de courtiers dans l'un ou plusieurs des domaines suivants : vente ou achat de biens immobiliers, location de biens immobiliers, prestation d'autres services liés à l'immobilier tels que l'évaluation de biens immobiliers ou l'activité d'agent fiduciaire en immobilier. Les activités de cette section peuvent être effectuées sur des biens propres ou loués, éventuellement pour le compte de tiers. Est également compris la promotion immobilière en vue d'une exploitation propre.</p>\n        <p>Cette section comprend aussi les gestionnaires de biens immobiliers.</p>\n    </div:div>\n"
}
